{
  "mod_lavacow:mod_lavacow/root": {
    "criteria": {
      "tick": "2024-01-15 00:41:09 +0000"
    },
    "done": true
  },
  "astralsorcery:root": {
    "criteria": {
      "astralsorcery_present": "2024-01-15 00:41:09 +0000"
    },
    "done": true
  },
  "galacticraftcore:galacticraft/root": {
    "criteria": {
      "tick": "2024-01-15 00:41:09 +0000"
    },
    "done": true
  },
  "mowziesmobs:root": {
    "criteria": {
      "custom_test_name": "2024-01-15 00:41:09 +0000"
    },
    "done": true
  },
  "cfm:root": {
    "criteria": {
      "tick": "2024-01-15 00:41:09 +0000"
    },
    "done": true
  },
  "twilightforest:alt/compat/tconstruct": {
    "criteria": {
      "book": "2024-01-15 00:41:09 +0000"
    },
    "done": true
  },
  "cfm:install": {
    "criteria": {
      "tick": "2024-01-15 00:41:09 +0000"
    },
    "done": true
  },
  "mysticalworld:root": {
    "criteria": {
      "auto": "2024-01-15 00:41:09 +0000"
    },
    "done": true
  },
  "minecraft:adventure/adventuring_time": {
    "criteria": {
      "beaches": "2024-01-15 00:41:23 +0000",
      "plains": "2024-01-15 00:41:09 +0000"
    },
    "done": false
  }
}